<?xml version="1.0" encoding="utf-8"?>
<LangFile xmlns:xsi="http://www.w3.org/2001/XMLSchema-instance" xmlns:xsd="http://www.w3.org/2001/XMLSchema" Endianess="BigEndian">
  <Entries>
    <Entry LangId="staff_hideo_kojima" Color="1" Value="Hideo Kojima" />
    <Entry LangId="staff_kenichiro_imaizumi" Color="1" Value="Kenichiro Imaizumi" />
    <Entry LangId="staff_kjp" Color="1" Value="Kojima Productions Presents" />
    <Entry LangId="staff_yuji_korekado" Color="1" Value="Yuji Korekado" />
    <Entry LangId="staff_ikuya_nakamura" Color="1" Value="Ikuya Nakamura" />
    <Entry LangId="staff_yoshikazu_matsuhana" Color="1" Value="Yoshikazu Matsuhana" />
    <Entry LangId="staff_hidenari_inamura" Color="1" Value="Hidenari Inamura" />
    <Entry LangId="staff_shuyo_murata" Color="1" Value="Shuyo Murata" />
    <Entry LangId="staff_etsu_tamari" Color="1" Value="Etsu Tamari" />
    <Entry LangId="staff_satoshi_matsuno" Color="1" Value="Satoshi Matsuno" />
    <Entry LangId="staff_tsuyoshi_osada" Color="1" Value="Tsuyoshi Osada" />
    <Entry LangId="staff_jordan_amaro" Color="1" Value="Jordan Amaro" />
    <Entry LangId="staff_takashi_hanyu" Color="1" Value="Takashi Hanyu" />
    <Entry LangId="staff_atsuki_imada" Color="1" Value="Atsuki Imada" />
    <Entry LangId="staff_takuya_imaeda" Color="1" Value="Takuya Imaeda" />
    <Entry LangId="staff_nobuyuki_imai" Color="1" Value="Nobuyuki Imai" />
    <Entry LangId="staff_tadashi_iwatou" Color="1" Value="Tadashi Iwatou" />
    <Entry LangId="staff_yuji_kaine" Color="1" Value="Yuji Kaine" />
    <Entry LangId="staff_youngho_kim" Color="1" Value="Youngho Kim" />
    <Entry LangId="staff_tadanobu_kishi" Color="1" Value="Tadanobu Kishi" />
    <Entry LangId="staff_yosuke_kitazono" Color="1" Value="Yosuke Kitazono" />
    <Entry LangId="staff_arata_matsushita" Color="1" Value="Arata Matsushita" />
    <Entry LangId="staff_ryo_nagatsuka" Color="1" Value="Ryo Nagatsuka" />
    <Entry LangId="staff_takashi_nakagawa" Color="1" Value="Takashi Nakagawa" />
    <Entry LangId="staff_yu_sahara" Color="1" Value="Yu Sahara" />
    <Entry LangId="staff_masaki_saito" Color="1" Value="Masaki Saito" />
    <Entry LangId="staff_kazuki_sakai" Color="1" Value="Kazuki Sakai" />
    <Entry LangId="staff_naoyuki_shiraishi" Color="1" Value="Naoyuki Shiraishi" />
    <Entry LangId="staff_takuya_sokukawa" Color="1" Value="Takuya Sokukawa" />
    <Entry LangId="staff_runa_sugiyama" Color="1" Value="Runa Sugiyama" />
    <Entry LangId="staff_takayoshi_takeuchi" Color="1" Value="Takayoshi Takeuchi" />
    <Entry LangId="staff_ziang_tan" Color="1" Value="Ziang Tan" />
    <Entry LangId="staff_yusuke_tanaka" Color="1" Value="Yusuke Tanaka" />
    <Entry LangId="staff_yota_tsutsumizaki" Color="1" Value="Yota Tsutsumizaki" />
    <Entry LangId="staff_takeo_yagi" Color="1" Value="Takeo Yagi" />
    <Entry LangId="staff_mokuto_yamamoto" Color="1" Value="Mokuto Yamamoto" />
    <Entry LangId="staff_shinpei_yamamoto" Color="1" Value="Shinpei Yamamoto" />
    <Entry LangId="staff_hiroaki_yoshiike" Color="1" Value="Hiroaki Yoshiike" />
    <Entry LangId="post_directed_by" Color="1" Value="Directed by" />
    <Entry LangId="post_guest_characters" Color="1" Value="Guest Starring" />
    <Entry LangId="post_level_design" Color="1" Value="Level Design" />
    <Entry LangId="post_producers" Color="1" Value="Producers" />
    <Entry LangId="post_starring" Color="1" Value="Starring" />
    <Entry LangId="post_wrriten_by" Color="1" Value="Written by" />
    <Entry LangId="cast_kazuhira_miller" Color="1" Value="Benedict &quot;Kazuhira&quot; Miller" />
    <Entry LangId="cast_sharashka_ocelot" Color="1" Value="Revolver &quot;Shalashaska&quot; Ocelot" />
    <Entry LangId="cast_soldier_skulls" Color="1" Value="The &quot;SKULLS&quot; Parasite Unit" />
    <Entry LangId="cast_soviet_soldiers" Color="1" Value="The Soviet Guards Airborne Regiment" />
    <Entry LangId="cast_venom_snake" Color="1" Value="Punished &quot;Venom&quot; Snake" />
    <Entry LangId="etc_and" Color="1" Value="AND" />
    <Entry Key="4153173125" Color="1" Value="J.F.Rey Eyewear" />
    <Entry Key="3047137944" Color="1" Value="JF1142" />
    <Entry LangId="cast_american_technician" Color="1" Value="The American Technician" />
    <Entry LangId="cast_arms_dealer" Color="1" Value="The Arms Dealer" />
    <Entry LangId="cast_bionics_engineer" Color="1" Value="The Bionics Engineer" />
    <Entry LangId="cast_cfa" Color="1" Value="The Contract Forces of Africa" />
    <Entry LangId="cast_cfa_executive" Color="1" Value="The CFA Executive" />
    <Entry LangId="cast_child_soldiers" Color="1" Value="Child Soldiers" />
    <Entry LangId="cast_child_soldiers_leader" Color="1" Value="Leader of the Child Soldiers" />
    <Entry LangId="cast_chopper_pilot" Color="1" Value="Chopper Pilot" />
    <Entry LangId="cast_code_talker" Color="1" Value="Old Diné &quot;Code Talker&quot;" />
    <Entry LangId="cast_da_shago_kallai_platoon_cmdr" Color="1" Value="Shago Platoon Commander" />
    <Entry LangId="cast_da_wialo_kallai_company_cmdr" Color="1" Value="Wialo Company Commander" />
    <Entry LangId="cast_diamond_dog_soldiers" Color="1" Value="Diamond Dog Soldiers" />
    <Entry LangId="cast_emmerich" Color="1" Value="Dr. &quot;Huey&quot; Emmerich" />
    <Entry LangId="cast_gunsmith" Color="1" Value="Gunsmith" />
    <Entry LangId="cast_hamid_fighters_mujahid" Color="1" Value="Hamid Mujahideen Survivor" />
    <Entry LangId="cast_intel_team_member" Color="1" Value="The Intel Team Member" />
    <Entry LangId="cast_intel_team_members" Color="1" Value="Intel Team Members" />
    <Entry LangId="cast_ishmael" Color="1" Value="ISHMAEL" />
    <Entry LangId="cast_lamar_khaate_palace_prisoner_escort" Color="1" Value="Lamar Khaate Palace Prisoner Escort" />
    <Entry LangId="cast_major" Color="1" Value="&quot;The Major&quot;" />
    <Entry LangId="cast_malak" Color="1" Value="Malak" />
    <Entry LangId="cast_man_on_fire" Color="1" Value="The Man on Fire" />
    <Entry LangId="cast_mbelle_prisoner" Color="1" Value="The Mbele Prisoner" />
    <Entry LangId="cast_mbelle_squad" Color="1" Value="The Mbele Squad" />
    <Entry Key="3101264743" Color="1" Value="Militants' No.2" />
    <Entry LangId="cast_mosquito" Color="1" Value="Mosquito" />
    <Entry LangId="cast_quiet" Color="1" Value="Sniper &quot;Quiet&quot;" />
    <Entry LangId="cast_rogue_coyote" Color="1" Value="Rogue Coyote" />
    <Entry LangId="cast_sahelanthropus" Color="1" Value="Sahelanthropus" />
    <Entry LangId="cast_sakhra_ee_village_colonel" Color="1" Value="Sakhra Ee Village Colonel" />
    <Entry LangId="cast_shabani" Color="1" Value="Shabani" />
    <Entry LangId="cast_skull_face" Color="1" Value="Skull Face" />
    <Entry LangId="cast_snake" Color="1" Value="SNAKE" />
    <Entry Key="432169502" Color="1" Value="Diamond Dog Soldiers" />
    <Entry Key="1951024377" Color="1" Value="Soldier &quot;Mist Unit&quot;" />
    <Entry LangId="cast_spetsnaz_commander" Color="1" Value="The Spetsnaz Commander" />
    <Entry LangId="cast_technicians_assistant" Color="1" Value="The Technician's Assistant" />
    <Entry LangId="cast_trafficker" Color="1" Value="The Trafficker" />
    <Entry LangId="cast_tretij_rebenok" Color="1" Value="Tretij Rebenok" />
    <Entry LangId="cast_tt-77" Color="1" Value="Battle Tank &quot;TT77 Nosorog&quot;" />
    <Entry LangId="cast_viscount" Color="1" Value="&quot;The Viscount&quot;" />
    <Entry LangId="cast_volgin" Color="1" Value="VOLGIN" />
    <Entry LangId="cast_wakh_sind_barracks_platoon_cmdr" Color="1" Value="Wakh Sind Platoon Commander" />
    <Entry LangId="cast_white_manba" Color="1" Value="Eli the &quot;White Mamba&quot;" />
    <Entry LangId="cast_zerorisk_security" Color="1" Value="Zero Risk Security" />
    <Entry LangId="post_special_mechanic" Color="1" Value="Featured Mecha" />
    <Entry LangId="staff_satoshi_hirano" Color="1" Value="Satoshi Hirano" />
    <Entry LangId="telop_kde_presents" Color="1" Value="KONAMI DIGITAL ENTERTAINMENT PRESENTS" />
    <Entry LangId="telop_kjp" Color="1" Value="KOJIMA PRODUCTIONS" />
    <Entry LangId="telop_hideo_kojima_game" Color="1" Value="A HIDEO KOJIMA GAME" />
    <Entry LangId="staff_Akihiro_Honda" Color="1" Value="Akihiro Honda" />
    <Entry LangId="staff_Akihiro_Teruta" Color="1" Value="Akihiro Teruta" />
    <Entry LangId="staff_Akira_Kanke" Color="1" Value="Akira Kanke" />
    <Entry LangId="staff_Brian_Robison" Color="1" Value="Brian Robison" />
    <Entry LangId="staff_Harry_Gregson-Williams" Color="1" Value="Harry Gregson-Williams" />
    <Entry LangId="staff_Hideki_Sasaki" Color="1" Value="Hideki Sasaki" />
    <Entry LangId="staff_Junji_Tago" Color="1" Value="Junji Tago" />
    <Entry LangId="staff_Kazuki_Muraoka" Color="1" Value="Kazuki Muraoka" />
    <Entry LangId="staff_Keiichi_Matate" Color="1" Value="Keiichi Matate" />
    <Entry LangId="staff_Kotaro_Oki" Color="1" Value="Kotaro Oki" />
    <Entry LangId="staff_Ludvig_Forssell" Color="1" Value="Ludvig Forssell" />
    <Entry LangId="staff_Makoto_Sonoyama" Color="1" Value="Makoto Sonoyama" />
    <Entry LangId="staff_Masaaki_Kawata" Color="1" Value="Masaaki Kawata" />
    <Entry LangId="staff_Masayuki_Suzuki" Color="1" Value="Masayuki Suzuki" />
    <Entry LangId="staff_Mineshi_Kimura" Color="1" Value="Mineshi Kimura" />
    <Entry LangId="staff_Motosada_Mori" Color="1" Value="Motosada Mori" />
    <Entry LangId="staff_Norifumi_Hosoya" Color="1" Value="Norifumi Hosoya" />
    <Entry LangId="staff_Ryoji_Makimura" Color="1" Value="Ryoji Makimura" />
    <Entry LangId="staff_Steve_Henifin" Color="1" Value="Steve Henifin" />
    <Entry LangId="staff_Takehiro_Nomura" Color="1" Value="Takehiro Nomura" />
    <Entry LangId="staff_Takeya_Inoguchi" Color="1" Value="Takeya Inoguchi" />
    <Entry LangId="staff_Tsuyoshi_Osada" Color="1" Value="Tsuyoshi Osada" />
    <Entry LangId="staff_Yasuhiro_Ikoma" Color="1" Value="Yasuhiro Ikoma" />
    <Entry LangId="staff_Yoji_Shinkawa" Color="1" Value="Yoji Shinkawa" />
    <Entry LangId="staff_Yoshiharu_Nishiyama" Color="1" Value="Yoshiharu Nishiyama" />
    <Entry LangId="staff_Justin_Burnett" Color="1" Value="Justin Burnett" />
    <Entry Key="4055020169" Color="1" Value="Story / Planning / Game Design" />
    <Entry LangId="post_Character_Mechanical_Design" Color="1" Value="Character &amp; Mechanical Design" />
    <Entry LangId="post_Music_Produced_by" Color="1" Value="Music Produced by" />
    <Entry LangId="post_Music_by" Color="1" Value="Music by" />
    <Entry LangId="post_Lighting_Supervisor" Color="1" Value="Lighting Supervisor" />
    <Entry LangId="post_Lead_Level_Designers" Color="1" Value="Lead Level Designers" />
    <Entry LangId="post_Lead_Programmers" Color="1" Value="Lead Programmers" />
    <Entry LangId="post_Technical_Director" Color="1" Value="Technical Director" />
    <Entry LangId="post_CG_Art_Director" Color="1" Value="CG Art Director" />
    <Entry LangId="post_Lead_Character_Artist" Color="1" Value="Lead Character Artist" />
    <Entry LangId="post_Lead_Weapon_Mechanical_Artist" Color="1" Value="Lead Weapon / Mechanical Artist" />
    <Entry LangId="post_Lead_Environment_Artist" Color="1" Value="Lead Environment Artist" />
    <Entry LangId="post_Lead_Effects_Artist" Color="1" Value="Lead Effects Artist" />
    <Entry LangId="post_Lead_UI_Artist" Color="1" Value="Lead UI Artist" />
    <Entry LangId="post_Lead_Animator" Color="1" Value="Lead Animator" />
    <Entry LangId="post_Lead_Cinematic_Artist" Color="1" Value="Lead Cinematic Artist" />
    <Entry Key="3836907221" Color="1" Value="Lead Lighting Artist" />
    <Entry LangId="post_Sound_Director" Color="1" Value="Sound Director" />
    <Entry LangId="post_Lead_Composer" Color="1" Value="Lead Composer" />
    <Entry LangId="post_Composer" Color="1" Value="Composer" />
    <Entry LangId="post_Lead_Sound_Designer" Color="1" Value="Lead Sound Designer" />
    <Entry LangId="post_Lead_Sound_Editor" Color="1" Value="Lead Sound Editor" />
    <Entry LangId="post_Art_Director" Color="1" Value="Art Director" />
    <Entry LangId="post_Co-Director" Color="1" Value="Co-Director" />
    <Entry LangId="post_Creative_Producers" Color="1" Value="Creative Producers" />
    <Entry LangId="post_Military_Advisor" Color="1" Value="Military Advisor" />
    <Entry LangId="act_Kiefer_Sutherland" Color="1" Value="Kiefer Sutherland" />
    <Entry LangId="act_Robin_Atkin_Downes" Color="1" Value="Robin Atkin Downes" />
    <Entry LangId="act_Troy_Baker" Color="1" Value="Troy Baker" />
    <Entry LangId="act_Stefanie_Joosten" Color="1" Value="Stefanie Joosten" />
    <Entry LangId="act_Christopher_Randolph" Color="1" Value="Christopher Randolph" />
    <Entry LangId="act_Piers_Stubbs" Color="1" Value="Piers Stubbs" />
    <Entry LangId="act_Jay_Tavare" Color="1" Value="Jay Tavare" />
    <Entry LangId="act_James_Horan" Color="1" Value="James Horan" />
    <Entry LangId="act_Time_Winters" Color="1" Value="Time Winters" />
    <Entry LangId="act_Tara_Strong" Color="1" Value="Tara Strong" />
    <Entry LangId="act_Dave_Fouquette" Color="1" Value="Dave Fouquette" />
    <Entry LangId="act_Vanessa_Marshall" Color="1" Value="Vanessa Marshall" />
    <Entry LangId="act_Lori_Alan" Color="1" Value="Lori Alan" />
    <Entry LangId="act_Akio_Ohtsuka" Color="1" Value="Akio Ohtsuka" />
    <Entry LangId="act_Tomokazu_Sugita" Color="1" Value="Tomokazu Sugita" />
    <Entry LangId="act_Satoshi_Mikami" Color="1" Value="Satoshi Mikami" />
    <Entry LangId="act_Hideyuki_Tanaka" Color="1" Value="Hideyuki Tanaka" />
    <Entry LangId="act_Osamu_Saka" Color="1" Value="Osamu Saka" />
    <Entry LangId="act_Yutaro_Honjo" Color="1" Value="Yutaro Honjo" />
    <Entry LangId="act_Banjo_Ginga" Color="1" Value="Banjo Ginga" />
    <Entry LangId="act_Nana_Mizuki" Color="1" Value="Nana Mizuki" />
    <Entry LangId="act_Yumi_Kikuchi" Color="1" Value="Yumi Kikuchi" />
    <Entry LangId="act_Kikuko_Inoue" Color="1" Value="Kikuko Inoue" />
    <Entry LangId="post_Enemy_Combatants" Color="1" Value="Enemy Combatants" />
    <Entry LangId="cast_Spetsnaz" Color="1" Value="Spetsnaz" />
    <Entry LangId="cast_Walker_Gear" Color="1" Value="Walker Gear" />
    <Entry LangId="cast_XOF" Color="1" Value="Cipher's &quot;XOF&quot; Strike Force" />
    <Entry LangId="cast_Eli" Color="1" Value="Eli the &quot;White Mamba&quot;" />
    <Entry LangId="cast_The_CIA_Agent" Color="1" Value="The CIA Agent" />
    <Entry LangId="cast_The_XOF_Agent" Color="1" Value="The XOF Agent" />
    <Entry LangId="cast_Lufwa_Valley_Commander" Color="1" Value="Lufwa Valley Commander" />
    <Entry LangId="cast_Armored_Column_Commander" Color="1" Value="Armored Column Commander" />
    <Entry LangId="act_Takaya_Hashi" Color="1" Value="Takaya Hashi" />
    <Entry LangId="act_Donna_Burke" Color="1" Value="Donna Burke" />
    <Entry LangId="post_idroid" Color="1" Value="iDROID" />
    <Entry LangId="act_Christos_Vasilopulous" Color="1" Value="Christos Vasilopoulos" />
    <Entry LangId="act_Hochu_Otsuka" Color="1" Value="Hochu Otsuka" />
    <Entry LangId="cast_HP-48_Krokodil" Color="1" Value="Attack Helicopter &quot;HP-48 Krokodil&quot;" />
    <Entry LangId="cast_Zhuk_RS-ZO" Color="1" Value="Multi-Rocket Launcher &quot;Zhuk RS-ZO&quot;" />
    <Entry LangId="cast_UTH-66_Blackfoot" Color="1" Value="Utility Helicopter &quot;UTH-66 Blackfoot&quot;" />
    <Entry LangId="cast_Stout_IFV-FS" Color="1" Value="Fire Support Vehicle &quot;Stout IFV-FS&quot;" />
    <Entry LangId="cast_M84A_Magloader" Color="1" Value="Battle Tank &quot;M84A Magloader&quot;" />
    <Entry LangId="post_Created_and_Directed_by" Color="1" Value="Created and Directed by" />
    <Entry LangId="cast_big_boss" Color="1" Value="Big Boss" />
    <Entry LangId="cast_paz" Color="1" Value="&quot;Paz&quot; Pacifica Ocean" />
    <Entry Key="2470051406" Color="1" Value="OCELOT GEAR" />
    <Entry Key="4005636992" Color="1" Value="KAZ GEAR" />
    <Entry Key="357703420" Color="1" Value="HIDEO GEAR" />
    <Entry LangId="staff_Xinpeng_Huang" Color="1" Value="Xinpeng Huang" />
    <Entry LangId="staff_Julien_Merceron" Color="1" Value="Julien Merceron" />
    <Entry LangId="staff_Shutaro_Iida" Color="1" Value="Shutaro Iida" />
    <Entry LangId="staff_Kazuki_Yanashima" Color="1" Value="Kazuki Yanashima" />
    <Entry LangId="staff_Masao_Awaji" Color="1" Value="Masao Awaji" />
    <Entry LangId="staff_Yusuke_Nishida" Color="1" Value="Yusuke Nishida" />
    <Entry LangId="staff_Masayuki_Kobayashi" Color="1" Value="Masayuki Kobayashi" />
    <Entry LangId="staff_Akio_Sakamoto" Color="1" Value="Akio Sakamoto" />
    <Entry LangId="staff_Kunio_Takabe" Color="1" Value="Kunio Takabe" />
    <Entry LangId="staff_Hironobu_Matsui" Color="1" Value="Hironobu Matsui" />
    <Entry LangId="staff_Yoshikazu_Hara" Color="1" Value="Yoshikazu Hara" />
    <Entry LangId="staff_Takayuki_Uchida" Color="1" Value="Takayuki Uchida" />
    <Entry LangId="staff_Noriaki_Nishimura" Color="1" Value="Noriaki Nishimura" />
    <Entry LangId="post_Technical_Supervisor" Color="1" Value="Technical Supervisor" />
    <Entry LangId="post_Lead_Planners" Color="1" Value="Lead Planners" />
    <Entry LangId="post_Lead_Scripter" Color="1" Value="Lead Scripter" />
    <Entry LangId="post_UI_Design" Color="1" Value="UI Design" />
    <Entry LangId="post_Lead_Programmer" Color="1" Value="Lead Programmer" />
    <Entry LangId="post_Lead_Game_Programmers" Color="1" Value="Lead Game Programmers" />
    <Entry LangId="post_Lead_UI_Programmer" Color="1" Value="Lead UI Programmer" />
    <Entry LangId="post_Lead_FX_Programmer" Color="1" Value="Lead FX Programmer" />
    <Entry LangId="post_Lead_Animation_Programmer" Color="1" Value="Lead Animation Programmer" />
    <Entry LangId="post_Lead_Network_Programmer" Color="1" Value="Lead Network Programmer" />
    <Entry LangId="post_Technical_Directors" Color="1" Value="Technical Directors" />
    <Entry LangId="post_CG_Art_Director" Color="1" Value="CG Art Director" />
    <Entry LangId="post_Lead_Character_Artists" Color="1" Value="Lead Character Artists" />
    <Entry LangId="post_Lead_Weapon_Mechanical_Artists" Color="1" Value="Lead Weapon / Mechanical Artists" />
    <Entry LangId="post_Lead_Environment_Artists" Color="1" Value="Lead Environment Artists" />
    <Entry LangId="post_Lead_Effects_Artist" Color="1" Value="Lead Effects Artist" />
    <Entry LangId="post_Lead_UI_Artist" Color="1" Value="Lead UI Artist" />
    <Entry LangId="staff_Noriaki_Okamura" Color="1" Value="Noriaki Okamura" />
    <Entry LangId="staff_Daizaburo_Nakamura" Color="1" Value="Daizaburo Nakamura" />
    <Entry LangId="cast_quiet_ene" Color="1" Value="Sniper &quot;Quiet&quot;" />
    <Entry LangId="post_Lead_Cinematic_Artists" Color="1" Value="Lead Cinematic Artists" />
  </Entries>
</LangFile>